{"name":"pixi","content":{"./node_modules/_@pixi_utils@5.2.4@@pixi/utils/lib/utils.es.js":{"id":0,"buildMeta":{"exportsType":"namespace","providedExports":["isMobile","EventEmitter","earcut","url","BaseTextureCache","CanvasRenderTarget","DATA_URI","ProgramCache","TextureCache","clearTextureCache","correctBlendMode","createIndicesForQuads","decomposeDataUri","deprecation","destroyTextureCache","determineCrossOrigin","getBufferType","getResolutionOfUrl","hex2rgb","hex2string","interleaveTypedArrays","isPow2","isWebGLSupported","log2","nextPow2","premultiplyBlendMode","premultiplyRgba","premultiplyTint","premultiplyTintToRgba","removeItems","rgb2hex","sayHello","sign","skipHello","string2hex","trimCanvas","uid"]}},"./node_modules/_@pixi_core@5.2.4@@pixi/core/lib/core.es.js":{"id":1,"buildMeta":{"exportsType":"namespace","providedExports":["AbstractBatchRenderer","AbstractRenderer","Attribute","BaseRenderTexture","BaseTexture","BatchDrawCall","BatchGeometry","BatchPluginFactory","BatchRenderer","BatchShaderGenerator","BatchTextureArray","Buffer","CubeTexture","Filter","Framebuffer","GLProgram","GLTexture","Geometry","MaskData","ObjectRenderer","Program","Quad","QuadUv","RenderTexture","RenderTexturePool","Renderer","Shader","SpriteMaskFilter","State","System","Texture","TextureMatrix","TextureUvs","UniformGroup","ViewableBuffer","autoDetectRenderer","checkMaxIfStatementsInShader","defaultFilterVertex","defaultVertex","resources","systems"]}},"./node_modules/_@pixi_constants@5.2.4@@pixi/constants/lib/constants.es.js":{"id":2,"buildMeta":{"exportsType":"namespace","providedExports":["ALPHA_MODES","BLEND_MODES","DRAW_MODES","ENV","FORMATS","GC_MODES","MASK_TYPES","MIPMAP_MODES","PRECISION","RENDERER_TYPE","SCALE_MODES","TARGETS","TYPES","WRAP_MODES"]}},"./node_modules/_@pixi_math@5.2.4@@pixi/math/lib/math.es.js":{"id":3,"buildMeta":{"exportsType":"namespace","providedExports":["Circle","DEG_TO_RAD","Ellipse","Matrix","ObservablePoint","PI_2","Point","Polygon","RAD_TO_DEG","Rectangle","RoundedRectangle","SHAPES","Transform","groupD8"]}},"./node_modules/_@pixi_settings@5.2.4@@pixi/settings/lib/settings.es.js":{"id":4,"buildMeta":{"exportsType":"namespace","providedExports":["isMobile","settings"]}},"./node_modules/_@pixi_display@5.2.4@@pixi/display/lib/display.es.js":{"id":5,"buildMeta":{"exportsType":"namespace","providedExports":["Bounds","Container","DisplayObject"]}},"./node_modules/_@pixi_ticker@5.2.4@@pixi/ticker/lib/ticker.es.js":{"id":6,"buildMeta":{"exportsType":"namespace","providedExports":["Ticker","TickerPlugin","UPDATE_PRIORITY"]}},"./node_modules/_@pixi_runner@5.2.4@@pixi/runner/lib/runner.es.js":{"id":7,"buildMeta":{"exportsType":"namespace","providedExports":["Runner"]}},"./node_modules/_@pixi_sprite@5.2.4@@pixi/sprite/lib/sprite.es.js":{"id":8,"buildMeta":{"exportsType":"namespace","providedExports":["Sprite"]}},"./node_modules/_@pixi_loaders@5.2.4@@pixi/loaders/lib/loaders.es.js":{"id":9,"buildMeta":{"exportsType":"namespace","providedExports":["AppLoaderPlugin","Loader","LoaderResource","TextureLoader"]}},"./node_modules/_@pixi_mesh@5.2.4@@pixi/mesh/lib/mesh.es.js":{"id":10,"buildMeta":{"exportsType":"namespace","providedExports":["Mesh","MeshBatchUvs","MeshGeometry","MeshMaterial"]}},"./node_modules/_mini-signals@1.2.0@mini-signals/lib/mini-signals.js":{"id":11,"buildMeta":{"providedExports":true}},"./node_modules/_@pixi_filter-kawase-blur@3.1.1@@pixi/filter-kawase-blur/lib/filter-kawase-blur.esm.js":{"id":12,"buildMeta":{"exportsType":"namespace","providedExports":["KawaseBlurFilter"]}},"./node_modules/_@pixi_text@5.2.4@@pixi/text/lib/text.es.js":{"id":13,"buildMeta":{"exportsType":"namespace","providedExports":["TEXT_GRADIENT","Text","TextMetrics","TextStyle"]}},"./node_modules/_@pixi_filter-blur@5.2.4@@pixi/filter-blur/lib/filter-blur.es.js":{"id":14,"buildMeta":{"exportsType":"namespace","providedExports":["BlurFilter","BlurFilterPass"]}},"./node_modules/_webpack@4.43.0@webpack/buildin/global.js":{"id":15,"buildMeta":{"providedExports":true}},"./node_modules/_@pixi_app@5.2.4@@pixi/app/lib/app.es.js":{"id":16,"buildMeta":{"exportsType":"namespace","providedExports":["Application"]}},"./node_modules/_@pixi_graphics@5.2.4@@pixi/graphics/lib/graphics.es.js":{"id":17,"buildMeta":{"exportsType":"namespace","providedExports":["FillStyle","GRAPHICS_CURVES","Graphics","GraphicsData","GraphicsGeometry","LineStyle","graphicsUtils"]}},"./node_modules/_resource-loader@3.0.1@resource-loader/dist/resource-loader.esm.js":{"id":18,"buildMeta":{"exportsType":"namespace","providedExports":["Loader","Resource","async","encodeBinary","middleware"]}},"./node_modules/_ismobilejs@1.1.1@ismobilejs/esm/isMobile.js":{"id":19,"buildMeta":{"exportsType":"namespace","providedExports":["default"]}},"./node_modules/_@pixi_accessibility@5.2.4@@pixi/accessibility/lib/accessibility.es.js":{"id":20,"buildMeta":{"exportsType":"namespace","providedExports":["AccessibilityManager","accessibleTarget"]}},"./node_modules/_url@0.11.0@url/url.js":{"id":21,"buildMeta":{"providedExports":true}},"./node_modules/_@pixi_interaction@5.2.4@@pixi/interaction/lib/interaction.es.js":{"id":22,"buildMeta":{"exportsType":"namespace","providedExports":["InteractionData","InteractionEvent","InteractionManager","InteractionTrackingData","interactiveTarget"]}},"./node_modules/_@pixi_extract@5.2.4@@pixi/extract/lib/extract.es.js":{"id":23,"buildMeta":{"exportsType":"namespace","providedExports":["Extract"]}},"./node_modules/_@pixi_particles@5.2.4@@pixi/particles/lib/particles.es.js":{"id":24,"buildMeta":{"exportsType":"namespace","providedExports":["ParticleContainer","ParticleRenderer"]}},"./node_modules/_@pixi_prepare@5.2.4@@pixi/prepare/lib/prepare.es.js":{"id":25,"buildMeta":{"exportsType":"namespace","providedExports":["BasePrepare","CountLimiter","Prepare","TimeLimiter"]}},"./node_modules/_@pixi_spritesheet@5.2.4@@pixi/spritesheet/lib/spritesheet.es.js":{"id":26,"buildMeta":{"exportsType":"namespace","providedExports":["Spritesheet","SpritesheetLoader"]}},"./node_modules/_@pixi_sprite-tiling@5.2.4@@pixi/sprite-tiling/lib/sprite-tiling.es.js":{"id":27,"buildMeta":{"exportsType":"namespace","providedExports":["TilingSprite","TilingSpriteRenderer"]}},"./node_modules/_@pixi_text-bitmap@5.2.4@@pixi/text-bitmap/lib/text-bitmap.es.js":{"id":28,"buildMeta":{"exportsType":"namespace","providedExports":["BitmapFontLoader","BitmapText"]}},"./node_modules/_@pixi_filter-alpha@5.2.4@@pixi/filter-alpha/lib/filter-alpha.es.js":{"id":29,"buildMeta":{"exportsType":"namespace","providedExports":["AlphaFilter"]}},"./node_modules/_parse-uri@1.0.0@parse-uri/index.js":{"id":30,"buildMeta":{"providedExports":true}},"./node_modules/_eventemitter3@3.1.2@eventemitter3/index.js":{"id":31,"buildMeta":{"providedExports":true}},"./node_modules/_earcut@2.2.2@earcut/src/earcut.js":{"id":32,"buildMeta":{"providedExports":true}},"./node_modules/_@pixi_mesh-extras@5.2.4@@pixi/mesh-extras/lib/mesh-extras.es.js":{"id":33,"buildMeta":{"exportsType":"namespace","providedExports":["NineSlicePlane","PlaneGeometry","RopeGeometry","SimpleMesh","SimplePlane","SimpleRope"]}},"./node_modules/_@pixi_sprite-animated@5.2.4@@pixi/sprite-animated/lib/sprite-animated.es.js":{"id":34,"buildMeta":{"exportsType":"namespace","providedExports":["AnimatedSprite"]}},"./node_modules/_@pixi_filter-adjustment@3.1.1@@pixi/filter-adjustment/lib/filter-adjustment.esm.js":{"id":35,"buildMeta":{"exportsType":"namespace","providedExports":["AdjustmentFilter"]}},"./node_modules/_@pixi_filter-advanced-bloom@3.1.1@@pixi/filter-advanced-bloom/lib/filter-advanced-bloom.esm.js":{"id":36,"buildMeta":{"exportsType":"namespace","providedExports":["AdvancedBloomFilter"]}},"./node_modules/_@pixi_filter-ascii@3.1.1@@pixi/filter-ascii/lib/filter-ascii.esm.js":{"id":37,"buildMeta":{"exportsType":"namespace","providedExports":["AsciiFilter"]}},"./node_modules/_@pixi_filter-bevel@3.1.1@@pixi/filter-bevel/lib/filter-bevel.esm.js":{"id":38,"buildMeta":{"exportsType":"namespace","providedExports":["BevelFilter"]}},"./node_modules/_@pixi_filter-bloom@3.1.1@@pixi/filter-bloom/lib/filter-bloom.esm.js":{"id":39,"buildMeta":{"exportsType":"namespace","providedExports":["BloomFilter"]}},"./node_modules/_@pixi_filter-bulge-pinch@3.1.1@@pixi/filter-bulge-pinch/lib/filter-bulge-pinch.esm.js":{"id":40,"buildMeta":{"exportsType":"namespace","providedExports":["BulgePinchFilter"]}},"./node_modules/_@pixi_filter-color-map@3.1.1@@pixi/filter-color-map/lib/filter-color-map.esm.js":{"id":41,"buildMeta":{"exportsType":"namespace","providedExports":["ColorMapFilter"]}},"./node_modules/_@pixi_filter-color-overlay@3.1.1@@pixi/filter-color-overlay/lib/filter-color-overlay.esm.js":{"id":42,"buildMeta":{"exportsType":"namespace","providedExports":["ColorOverlayFilter"]}},"./node_modules/_@pixi_filter-color-replace@3.1.1@@pixi/filter-color-replace/lib/filter-color-replace.esm.js":{"id":43,"buildMeta":{"exportsType":"namespace","providedExports":["ColorReplaceFilter"]}},"./node_modules/_@pixi_filter-convolution@3.1.1@@pixi/filter-convolution/lib/filter-convolution.esm.js":{"id":44,"buildMeta":{"exportsType":"namespace","providedExports":["ConvolutionFilter"]}},"./node_modules/_@pixi_filter-cross-hatch@3.1.1@@pixi/filter-cross-hatch/lib/filter-cross-hatch.esm.js":{"id":45,"buildMeta":{"exportsType":"namespace","providedExports":["CrossHatchFilter"]}},"./node_modules/_@pixi_filter-crt@3.1.1@@pixi/filter-crt/lib/filter-crt.esm.js":{"id":46,"buildMeta":{"exportsType":"namespace","providedExports":["CRTFilter"]}},"./node_modules/_@pixi_filter-dot@3.1.1@@pixi/filter-dot/lib/filter-dot.esm.js":{"id":47,"buildMeta":{"exportsType":"namespace","providedExports":["DotFilter"]}},"./node_modules/_@pixi_filter-drop-shadow@3.1.1@@pixi/filter-drop-shadow/lib/filter-drop-shadow.esm.js":{"id":48,"buildMeta":{"exportsType":"namespace","providedExports":["DropShadowFilter"]}},"./node_modules/_@pixi_filter-emboss@3.1.1@@pixi/filter-emboss/lib/filter-emboss.esm.js":{"id":49,"buildMeta":{"exportsType":"namespace","providedExports":["EmbossFilter"]}},"./node_modules/_@pixi_filter-glitch@3.1.1@@pixi/filter-glitch/lib/filter-glitch.esm.js":{"id":50,"buildMeta":{"exportsType":"namespace","providedExports":["GlitchFilter"]}},"./node_modules/_@pixi_filter-glow@3.1.1@@pixi/filter-glow/lib/filter-glow.esm.js":{"id":51,"buildMeta":{"exportsType":"namespace","providedExports":["GlowFilter"]}},"./node_modules/_@pixi_filter-godray@3.1.1@@pixi/filter-godray/lib/filter-godray.esm.js":{"id":52,"buildMeta":{"exportsType":"namespace","providedExports":["GodrayFilter"]}},"./node_modules/_@pixi_filter-motion-blur@3.1.1@@pixi/filter-motion-blur/lib/filter-motion-blur.esm.js":{"id":53,"buildMeta":{"exportsType":"namespace","providedExports":["MotionBlurFilter"]}},"./node_modules/_@pixi_filter-multi-color-replace@3.1.1@@pixi/filter-multi-color-replace/lib/filter-multi-color-replace.esm.js":{"id":54,"buildMeta":{"exportsType":"namespace","providedExports":["MultiColorReplaceFilter"]}},"./node_modules/_@pixi_filter-old-film@3.1.1@@pixi/filter-old-film/lib/filter-old-film.esm.js":{"id":55,"buildMeta":{"exportsType":"namespace","providedExports":["OldFilmFilter"]}},"./node_modules/_@pixi_filter-outline@3.1.1@@pixi/filter-outline/lib/filter-outline.esm.js":{"id":56,"buildMeta":{"exportsType":"namespace","providedExports":["OutlineFilter"]}},"./node_modules/_@pixi_filter-pixelate@3.1.1@@pixi/filter-pixelate/lib/filter-pixelate.esm.js":{"id":57,"buildMeta":{"exportsType":"namespace","providedExports":["PixelateFilter"]}},"./node_modules/_@pixi_filter-radial-blur@3.1.1@@pixi/filter-radial-blur/lib/filter-radial-blur.esm.js":{"id":58,"buildMeta":{"exportsType":"namespace","providedExports":["RadialBlurFilter"]}},"./node_modules/_@pixi_filter-reflection@3.1.1@@pixi/filter-reflection/lib/filter-reflection.esm.js":{"id":59,"buildMeta":{"exportsType":"namespace","providedExports":["ReflectionFilter"]}},"./node_modules/_@pixi_filter-rgb-split@3.1.1@@pixi/filter-rgb-split/lib/filter-rgb-split.esm.js":{"id":60,"buildMeta":{"exportsType":"namespace","providedExports":["RGBSplitFilter"]}},"./node_modules/_@pixi_filter-shockwave@3.1.1@@pixi/filter-shockwave/lib/filter-shockwave.esm.js":{"id":61,"buildMeta":{"exportsType":"namespace","providedExports":["ShockwaveFilter"]}},"./node_modules/_@pixi_filter-simple-lightmap@3.1.1@@pixi/filter-simple-lightmap/lib/filter-simple-lightmap.esm.js":{"id":62,"buildMeta":{"exportsType":"namespace","providedExports":["SimpleLightmapFilter"]}},"./node_modules/_@pixi_filter-tilt-shift@3.1.1@@pixi/filter-tilt-shift/lib/filter-tilt-shift.esm.js":{"id":63,"buildMeta":{"exportsType":"namespace","providedExports":["TiltShiftAxisFilter","TiltShiftFilter","TiltShiftXFilter","TiltShiftYFilter"]}},"./node_modules/_@pixi_filter-twist@3.1.1@@pixi/filter-twist/lib/filter-twist.esm.js":{"id":64,"buildMeta":{"exportsType":"namespace","providedExports":["TwistFilter"]}},"./node_modules/_@pixi_filter-zoom-blur@3.1.1@@pixi/filter-zoom-blur/lib/filter-zoom-blur.esm.js":{"id":65,"buildMeta":{"exportsType":"namespace","providedExports":["ZoomBlurFilter"]}},"./node_modules/_es6-promise-polyfill@1.2.0@es6-promise-polyfill/promise.js":{"id":66,"buildMeta":{"providedExports":true}},"./node_modules/_object-assign@4.1.1@object-assign/index.js":{"id":67,"buildMeta":{"providedExports":true}},"./node_modules/_ismobilejs@1.1.1@ismobilejs/esm/index.js":{"id":68,"buildMeta":{"exportsType":"namespace","providedExports":["default"]}},"./node_modules/_@pixi_filter-color-matrix@5.2.4@@pixi/filter-color-matrix/lib/filter-color-matrix.es.js":{"id":69,"buildMeta":{"exportsType":"namespace","providedExports":["ColorMatrixFilter"]}},"./node_modules/_@pixi_filter-displacement@5.2.4@@pixi/filter-displacement/lib/filter-displacement.es.js":{"id":70,"buildMeta":{"exportsType":"namespace","providedExports":["DisplacementFilter"]}},"./node_modules/_@pixi_filter-fxaa@5.2.4@@pixi/filter-fxaa/lib/filter-fxaa.es.js":{"id":71,"buildMeta":{"exportsType":"namespace","providedExports":["FXAAFilter"]}},"./node_modules/_@pixi_filter-noise@5.2.4@@pixi/filter-noise/lib/filter-noise.es.js":{"id":72,"buildMeta":{"exportsType":"namespace","providedExports":["NoiseFilter"]}},"./node_modules/_pixi.js@5.2.4@pixi.js/lib/pixi.es.js":{"id":74,"buildMeta":{"exportsType":"namespace","providedExports":["accessibility","interaction","utils","Application","AbstractBatchRenderer","AbstractRenderer","Attribute","BaseRenderTexture","BaseTexture","BatchDrawCall","BatchGeometry","BatchPluginFactory","BatchRenderer","BatchShaderGenerator","BatchTextureArray","Buffer","CubeTexture","Filter","Framebuffer","GLProgram","GLTexture","Geometry","MaskData","ObjectRenderer","Program","Quad","QuadUv","RenderTexture","RenderTexturePool","Renderer","Shader","SpriteMaskFilter","State","System","Texture","TextureMatrix","TextureUvs","UniformGroup","ViewableBuffer","autoDetectRenderer","checkMaxIfStatementsInShader","defaultFilterVertex","defaultVertex","resources","systems","Extract","AppLoaderPlugin","Loader","LoaderResource","TextureLoader","ParticleContainer","ParticleRenderer","BasePrepare","CountLimiter","Prepare","TimeLimiter","Spritesheet","SpritesheetLoader","TilingSprite","TilingSpriteRenderer","BitmapFontLoader","BitmapText","Ticker","TickerPlugin","UPDATE_PRIORITY","ALPHA_MODES","BLEND_MODES","DRAW_MODES","ENV","FORMATS","GC_MODES","MASK_TYPES","MIPMAP_MODES","PRECISION","RENDERER_TYPE","SCALE_MODES","TARGETS","TYPES","WRAP_MODES","Bounds","Container","DisplayObject","FillStyle","GRAPHICS_CURVES","Graphics","GraphicsData","GraphicsGeometry","LineStyle","graphicsUtils","Circle","DEG_TO_RAD","Ellipse","Matrix","ObservablePoint","PI_2","Point","Polygon","RAD_TO_DEG","Rectangle","RoundedRectangle","SHAPES","Transform","groupD8","Mesh","MeshBatchUvs","MeshGeometry","MeshMaterial","NineSlicePlane","PlaneGeometry","RopeGeometry","SimpleMesh","SimplePlane","SimpleRope","Runner","Sprite","AnimatedSprite","TEXT_GRADIENT","Text","TextMetrics","TextStyle","isMobile","settings","VERSION","filters","useDeprecated"]}},"./node_modules/_@pixi_polyfill@5.2.4@@pixi/polyfill/lib/polyfill.es.js":{"id":75,"buildMeta":{"exportsType":"namespace","providedExports":[]}},"./node_modules/_timers-browserify@2.0.11@timers-browserify/main.js":{"id":76,"buildMeta":{"providedExports":true}},"./node_modules/_setimmediate@1.0.5@setimmediate/setImmediate.js":{"id":77,"buildMeta":{"providedExports":true}},"./node_modules/_process@0.11.10@process/browser.js":{"id":78,"buildMeta":{"providedExports":true}},"./node_modules/_punycode@1.4.1@punycode/punycode.js":{"id":79,"buildMeta":{"providedExports":true}},"./node_modules/_webpack@4.43.0@webpack/buildin/module.js":{"id":80,"buildMeta":{"providedExports":true}},"./node_modules/_url@0.11.0@url/util.js":{"id":81,"buildMeta":{"providedExports":true}},"./node_modules/_querystring-es3@0.2.1@querystring-es3/index.js":{"id":82,"buildMeta":{"providedExports":true}},"./node_modules/_querystring-es3@0.2.1@querystring-es3/decode.js":{"id":83,"buildMeta":{"providedExports":true}},"./node_modules/_querystring-es3@0.2.1@querystring-es3/encode.js":{"id":84,"buildMeta":{"providedExports":true}},"./node_modules/_@pixi_mixin-cache-as-bitmap@5.2.4@@pixi/mixin-cache-as-bitmap/lib/mixin-cache-as-bitmap.es.js":{"id":85,"buildMeta":{"exportsType":"namespace","providedExports":[]}},"./node_modules/_@pixi_mixin-get-child-by-name@5.2.4@@pixi/mixin-get-child-by-name/lib/mixin-get-child-by-name.es.js":{"id":86,"buildMeta":{"exportsType":"namespace","providedExports":[]}},"./node_modules/_@pixi_mixin-get-global-position@5.2.4@@pixi/mixin-get-global-position/lib/mixin-get-global-position.es.js":{"id":87,"buildMeta":{"exportsType":"namespace","providedExports":[]}},"./node_modules/_pixi-filters@3.1.1@pixi-filters/lib/pixi-filters.esm.js":{"id":88,"buildMeta":{"exportsType":"namespace","providedExports":["AdjustmentFilter","AdvancedBloomFilter","AsciiFilter","BevelFilter","BloomFilter","BulgePinchFilter","ColorMapFilter","ColorOverlayFilter","ColorReplaceFilter","ConvolutionFilter","CrossHatchFilter","CRTFilter","DotFilter","DropShadowFilter","EmbossFilter","GlitchFilter","GlowFilter","GodrayFilter","KawaseBlurFilter","MotionBlurFilter","MultiColorReplaceFilter","OldFilmFilter","OutlineFilter","PixelateFilter","RadialBlurFilter","ReflectionFilter","RGBSplitFilter","ShockwaveFilter","SimpleLightmapFilter","TiltShiftAxisFilter","TiltShiftFilter","TiltShiftXFilter","TiltShiftYFilter","TwistFilter","ZoomBlurFilter"]}}}}